plustools/__init__.py
plustools/analysis.py
plustools/combine.py
plustools/connector.py
plustools-0.0.15.dist-info/LICENSE
plustools-0.0.15.dist-info/METADATA
plustools-0.0.15.dist-info/WHEEL
plustools-0.0.15.dist-info/top_level.txt
plustools-0.0.15.dist-info/RECORD
