Metadata-Version: 2.1
Name: plustools
Version: 0.0.15
Summary: Tools to facilitate the automation of Aspen Plus through Python
Author: Albert Lenk
Author-email: albert.lenk@outlook.de
License: GNU GPLv3
Keywords: Python,Aspen Plus,Process Simulation,Automation
Classifier: Development Status :: 1 - Planning
Classifier: Programming Language :: Python :: 3
Classifier: Operating System :: Microsoft :: Windows
Classifier: Intended Audience :: Science/Research
Classifier: License :: OSI Approved :: GNU General Public License v3 (GPLv3)
License-File: LICENSE
Requires-Dist: pandas
Requires-Dist: pywin32
